r_lambda/__init__.py
r_lambda/docker.py
r_lambda/r_env.py
r_lambda/shell.py
r_lambda-1.1.2025.820.dist-info/LICENSE
r_lambda-1.1.2025.820.dist-info/METADATA
r_lambda-1.1.2025.820.dist-info/WHEEL
r_lambda-1.1.2025.820.dist-info/top_level.txt
r_lambda-1.1.2025.820.dist-info/RECORD
