Metadata-Version: 2.1
Name: r-lambda
Version: 1.1.2025.820
Summary: A simple commandline wrapper package for call a target R# function from commandline
Home-page: https://github.com/rsharp-lang/IronR
Author: xieguigang
Author-email: xie.guigang@gcmodeller.org
License: MIT
Requires-Python: >=3.6
License-File: LICENSE
